\hypertarget{definitions_8h_source}{}\doxysection{definitions.\+h}
\label{definitions_8h_source}\index{headers/definitions.h@{headers/definitions.h}}

\begin{DoxyCode}{0}
\DoxyCodeLine{1 \textcolor{comment}{/*}}
\DoxyCodeLine{2 \textcolor{comment}{Universidade de Brasília -\/ 2021/2}}
\DoxyCodeLine{3 \textcolor{comment}{Software Básico -\/ Turma A}}
\DoxyCodeLine{4 \textcolor{comment}{Trabalho: JVM}}
\DoxyCodeLine{5 \textcolor{comment}{Alunos:}}
\DoxyCodeLine{6 \textcolor{comment}{            Caio Bernardon N. K. Massucato – 16/0115001}}
\DoxyCodeLine{7 \textcolor{comment}{            Rafael Gonçalves de Paulo -\/ 17/0043959}}
\DoxyCodeLine{8 \textcolor{comment}{            José Vinícius Garreto Costa – 18/0123734}}
\DoxyCodeLine{9 \textcolor{comment}{            Alice da Costa Borges  -\/ 18/0011855}}
\DoxyCodeLine{10 \textcolor{comment}{            Lucas Vinicius Magalhães Pinheiro -\/ 17/0061001}}
\DoxyCodeLine{11 \textcolor{comment}{*/}}
\DoxyCodeLine{12 }
\DoxyCodeLine{13 \textcolor{preprocessor}{\#ifndef definitions\_h}}
\DoxyCodeLine{14 \textcolor{preprocessor}{\#define definitions\_h}}
\DoxyCodeLine{15 }
\DoxyCodeLine{21 \textcolor{preprocessor}{\#include <stdint.h>}}
\DoxyCodeLine{22 \textcolor{preprocessor}{\#include <iostream>}}
\DoxyCodeLine{23 }
\DoxyCodeLine{25 \textcolor{keyword}{typedef} uint8\_t u1;}
\DoxyCodeLine{26 \textcolor{keyword}{typedef} uint16\_t u2;}
\DoxyCodeLine{27 \textcolor{keyword}{typedef} uint32\_t u4;}
\DoxyCodeLine{28 }
\DoxyCodeLine{29 \textcolor{keyword}{typedef} int8\_t i1;   }
\DoxyCodeLine{30 \textcolor{keyword}{typedef} int16\_t i2;  }
\DoxyCodeLine{31 \textcolor{keyword}{typedef} int32\_t i4;  }
\DoxyCodeLine{32 \textcolor{keyword}{typedef} int64\_t i8;  }
\DoxyCodeLine{33 }
\DoxyCodeLine{34 \textcolor{preprocessor}{\#define CONSTANT\_Utf8 1}}
\DoxyCodeLine{35 \textcolor{preprocessor}{\#define CONSTANT\_Integer 3}}
\DoxyCodeLine{36 \textcolor{preprocessor}{\#define CONSTANT\_Float 4}}
\DoxyCodeLine{37 \textcolor{preprocessor}{\#define CONSTANT\_Long 5}}
\DoxyCodeLine{38 \textcolor{preprocessor}{\#define CONSTANT\_Double 6}}
\DoxyCodeLine{39 \textcolor{preprocessor}{\#define CONSTANT\_Class 7}}
\DoxyCodeLine{40 \textcolor{preprocessor}{\#define CONSTANT\_String 8}}
\DoxyCodeLine{41 \textcolor{preprocessor}{\#define CONSTANT\_Fieldref 9}}
\DoxyCodeLine{42 \textcolor{preprocessor}{\#define CONSTANT\_Methodref 10}}
\DoxyCodeLine{43 \textcolor{preprocessor}{\#define CONSTANT\_InterfaceMethodref 11}}
\DoxyCodeLine{44 \textcolor{preprocessor}{\#define CONSTANT\_NameAndType 12}}
\DoxyCodeLine{45 \textcolor{preprocessor}{\#define CONSTANT\_MethodHandle 15}}
\DoxyCodeLine{46 \textcolor{preprocessor}{\#define CONSTANT\_MethodType 16}}
\DoxyCodeLine{47 \textcolor{preprocessor}{\#define CONSTANT\_InvokeDynamic 18}}
\DoxyCodeLine{48 }
\DoxyCodeLine{49 \textcolor{preprocessor}{\#define ACC\_PUBLIC 0x0001 }}
\DoxyCodeLine{50 \textcolor{preprocessor}{\#define ACC\_PRIVATE 0x0002 }}
\DoxyCodeLine{51 \textcolor{preprocessor}{\#define ACC\_PROTECTED 0x0004 }}
\DoxyCodeLine{52 \textcolor{preprocessor}{\#define ACC\_STATIC 0x0008 }}
\DoxyCodeLine{53 \textcolor{preprocessor}{\#define ACC\_FINAL 0x0010 }}
\DoxyCodeLine{54 \textcolor{preprocessor}{\#define ACC\_SYNCHRONIZED 0x0020 }}
\DoxyCodeLine{55 \textcolor{preprocessor}{\#define ACC\_BRIDGE 0x0040 }}
\DoxyCodeLine{56 \textcolor{preprocessor}{\#define ACC\_VARARGS 0x0080 }}
\DoxyCodeLine{57 \textcolor{preprocessor}{\#define ACC\_NATIVE 0x0100 }}
\DoxyCodeLine{58 \textcolor{preprocessor}{\#define ACC\_ABSTRACT 0x0400 }}
\DoxyCodeLine{59 \textcolor{preprocessor}{\#define ACC\_STRICT 0x0800 }}
\DoxyCodeLine{60 \textcolor{preprocessor}{\#define ACC\_SYNTHETIC 0x1000 }}
\DoxyCodeLine{61 }
\DoxyCodeLine{62 }
\DoxyCodeLine{64 \textcolor{preprocessor}{\#define u1READ(arq) getc(arq)}}
\DoxyCodeLine{66 \textcolor{preprocessor}{\#define u2READ(arq) (getc(arq) << 8) | getc(arq)}}
\DoxyCodeLine{68 \textcolor{preprocessor}{\#define u4READ(arq) (getc(arq) << 24) | (getc(arq) << 16 | getc(arq) << 8 | getc(arq))}}
\DoxyCodeLine{69 }
\DoxyCodeLine{70 std::ostream\& indentBy(\textcolor{keywordtype}{unsigned} \textcolor{keywordtype}{int} n, std::ostream\& out = std::cout);}
\DoxyCodeLine{71 }
\DoxyCodeLine{73 \textcolor{preprocessor}{\#define nop 0x00}}
\DoxyCodeLine{74 \textcolor{preprocessor}{\#define aconst\_null 0x01}}
\DoxyCodeLine{75 \textcolor{preprocessor}{\#define iconst\_m1 0x02}}
\DoxyCodeLine{76 \textcolor{preprocessor}{\#define iconst\_0 0x03}}
\DoxyCodeLine{77 \textcolor{preprocessor}{\#define iconst\_2 0x05}}
\DoxyCodeLine{78 \textcolor{preprocessor}{\#define iconst\_1 0x04}}
\DoxyCodeLine{79 \textcolor{preprocessor}{\#define iconst\_3 0x06}}
\DoxyCodeLine{80 \textcolor{preprocessor}{\#define iconst\_4 0x07}}
\DoxyCodeLine{81 \textcolor{preprocessor}{\#define iconst\_5 0x08}}
\DoxyCodeLine{82 \textcolor{preprocessor}{\#define lconst\_0 0x09}}
\DoxyCodeLine{83 \textcolor{preprocessor}{\#define lconst\_1 0x0a}}
\DoxyCodeLine{84 \textcolor{preprocessor}{\#define fconst\_0 0x0b}}
\DoxyCodeLine{85 \textcolor{preprocessor}{\#define fconst\_1 0x0c}}
\DoxyCodeLine{86 \textcolor{preprocessor}{\#define fconst\_2 0x0d}}
\DoxyCodeLine{87 \textcolor{preprocessor}{\#define dconst\_0 0x0e}}
\DoxyCodeLine{88 \textcolor{preprocessor}{\#define dconst\_1 0x0f}}
\DoxyCodeLine{89 \textcolor{preprocessor}{\#define bipush 0x10}}
\DoxyCodeLine{90 \textcolor{preprocessor}{\#define sipush 0x11}}
\DoxyCodeLine{91 \textcolor{preprocessor}{\#define ldc 0x12}}
\DoxyCodeLine{92 \textcolor{preprocessor}{\#define ldc\_w 0x13}}
\DoxyCodeLine{93 \textcolor{preprocessor}{\#define ldc2\_w 0x14}}
\DoxyCodeLine{94 \textcolor{preprocessor}{\#define iload 0x15}}
\DoxyCodeLine{95 \textcolor{preprocessor}{\#define lload 0x16}}
\DoxyCodeLine{96 \textcolor{preprocessor}{\#define fload 0x17}}
\DoxyCodeLine{97 \textcolor{preprocessor}{\#define dload 0x18}}
\DoxyCodeLine{98 \textcolor{preprocessor}{\#define aload 0x19}}
\DoxyCodeLine{99 \textcolor{preprocessor}{\#define iload\_0 0x1a}}
\DoxyCodeLine{100 \textcolor{preprocessor}{\#define iload\_1 0x1b}}
\DoxyCodeLine{101 \textcolor{preprocessor}{\#define iload\_2 0x1c}}
\DoxyCodeLine{102 \textcolor{preprocessor}{\#define iload\_3 0x1d}}
\DoxyCodeLine{103 \textcolor{preprocessor}{\#define lload\_0 0x1e}}
\DoxyCodeLine{104 \textcolor{preprocessor}{\#define lload\_1 0x1f}}
\DoxyCodeLine{105 \textcolor{preprocessor}{\#define lload\_2 0x20}}
\DoxyCodeLine{106 \textcolor{preprocessor}{\#define lload\_3 0x21}}
\DoxyCodeLine{107 \textcolor{preprocessor}{\#define fload\_0 0x22}}
\DoxyCodeLine{108 \textcolor{preprocessor}{\#define fload\_1 0x23}}
\DoxyCodeLine{109 \textcolor{preprocessor}{\#define fload\_2 0x24}}
\DoxyCodeLine{110 \textcolor{preprocessor}{\#define fload\_3 0x25}}
\DoxyCodeLine{111 \textcolor{preprocessor}{\#define dload\_0 0x26}}
\DoxyCodeLine{112 \textcolor{preprocessor}{\#define dload\_1 0x27}}
\DoxyCodeLine{113 \textcolor{preprocessor}{\#define dload\_2 0x28}}
\DoxyCodeLine{114 \textcolor{preprocessor}{\#define dload\_3 0x29}}
\DoxyCodeLine{115 \textcolor{preprocessor}{\#define aload\_0 0x2a}}
\DoxyCodeLine{116 \textcolor{preprocessor}{\#define aload\_1 0x2b}}
\DoxyCodeLine{117 \textcolor{preprocessor}{\#define aload\_2 0x2c}}
\DoxyCodeLine{118 \textcolor{preprocessor}{\#define aload\_3 0x2d}}
\DoxyCodeLine{119 \textcolor{preprocessor}{\#define iaload 0x2e}}
\DoxyCodeLine{120 \textcolor{preprocessor}{\#define laload 0x2f}}
\DoxyCodeLine{121 \textcolor{preprocessor}{\#define faload 0x30}}
\DoxyCodeLine{122 \textcolor{preprocessor}{\#define daload 0x31}}
\DoxyCodeLine{123 \textcolor{preprocessor}{\#define aaload 0x32}}
\DoxyCodeLine{124 \textcolor{preprocessor}{\#define baload 0x33}}
\DoxyCodeLine{125 \textcolor{preprocessor}{\#define caload 0x34}}
\DoxyCodeLine{126 \textcolor{preprocessor}{\#define saload 0x35}}
\DoxyCodeLine{127 \textcolor{preprocessor}{\#define istore 0x36}}
\DoxyCodeLine{128 \textcolor{preprocessor}{\#define lstore 0x37}}
\DoxyCodeLine{129 \textcolor{preprocessor}{\#define fstore 0x38}}
\DoxyCodeLine{130 \textcolor{preprocessor}{\#define dstore 0x39}}
\DoxyCodeLine{131 \textcolor{preprocessor}{\#define astore 0x3a}}
\DoxyCodeLine{132 \textcolor{preprocessor}{\#define istore\_0 0x3b}}
\DoxyCodeLine{133 \textcolor{preprocessor}{\#define istore\_1 0x3c}}
\DoxyCodeLine{134 \textcolor{preprocessor}{\#define istore\_2 0x3d}}
\DoxyCodeLine{135 \textcolor{preprocessor}{\#define istore\_3 0x3e}}
\DoxyCodeLine{136 \textcolor{preprocessor}{\#define lstore\_0 0x3f}}
\DoxyCodeLine{137 \textcolor{preprocessor}{\#define lstore\_1 0x40}}
\DoxyCodeLine{138 \textcolor{preprocessor}{\#define lstore\_2 0x41}}
\DoxyCodeLine{139 \textcolor{preprocessor}{\#define lstore\_3 0x42}}
\DoxyCodeLine{140 \textcolor{preprocessor}{\#define fstore\_0 0x43}}
\DoxyCodeLine{141 \textcolor{preprocessor}{\#define fstore\_1 0x44}}
\DoxyCodeLine{142 \textcolor{preprocessor}{\#define fstore\_2 0x45}}
\DoxyCodeLine{143 \textcolor{preprocessor}{\#define fstore\_3 0x46}}
\DoxyCodeLine{144 \textcolor{preprocessor}{\#define dstore\_0 0x47}}
\DoxyCodeLine{145 \textcolor{preprocessor}{\#define dstore\_1 0x48}}
\DoxyCodeLine{146 \textcolor{preprocessor}{\#define dstore\_2 0x49}}
\DoxyCodeLine{147 \textcolor{preprocessor}{\#define dstore\_3 0x4a}}
\DoxyCodeLine{148 \textcolor{preprocessor}{\#define astore\_0 0x4b}}
\DoxyCodeLine{149 \textcolor{preprocessor}{\#define astore\_1 0x4c}}
\DoxyCodeLine{150 \textcolor{preprocessor}{\#define astore\_2 0x4d}}
\DoxyCodeLine{151 \textcolor{preprocessor}{\#define astore\_3 0x4e}}
\DoxyCodeLine{152 \textcolor{preprocessor}{\#define iastore 0x4f}}
\DoxyCodeLine{153 \textcolor{preprocessor}{\#define lastore 0x50}}
\DoxyCodeLine{154 \textcolor{preprocessor}{\#define fastore 0x51}}
\DoxyCodeLine{155 \textcolor{preprocessor}{\#define dastore 0x52}}
\DoxyCodeLine{156 \textcolor{preprocessor}{\#define aastore 0x53}}
\DoxyCodeLine{157 \textcolor{preprocessor}{\#define bastore 0x54}}
\DoxyCodeLine{158 \textcolor{preprocessor}{\#define castore 0x55}}
\DoxyCodeLine{159 \textcolor{preprocessor}{\#define sastore 0x56}}
\DoxyCodeLine{160 \textcolor{preprocessor}{\#define pop 0x57}}
\DoxyCodeLine{161 \textcolor{preprocessor}{\#define pop2 0x58}}
\DoxyCodeLine{162 \textcolor{preprocessor}{\#define dup 0x59}}
\DoxyCodeLine{163 \textcolor{preprocessor}{\#define dup\_x1 0x5a}}
\DoxyCodeLine{164 \textcolor{preprocessor}{\#define dup\_x2 0x5b}}
\DoxyCodeLine{165 \textcolor{preprocessor}{\#define dup2 0x5c}}
\DoxyCodeLine{166 \textcolor{preprocessor}{\#define dup2\_x1 0x5d}}
\DoxyCodeLine{167 \textcolor{preprocessor}{\#define dup2\_x2 0x5e}}
\DoxyCodeLine{168 \textcolor{preprocessor}{\#define swapSwap 0x5f}}
\DoxyCodeLine{169 \textcolor{preprocessor}{\#define iadd 0x60}}
\DoxyCodeLine{170 \textcolor{preprocessor}{\#define ladd 0x61}}
\DoxyCodeLine{171 \textcolor{preprocessor}{\#define fadd 0x62}}
\DoxyCodeLine{172 \textcolor{preprocessor}{\#define dadd 0x63}}
\DoxyCodeLine{173 \textcolor{preprocessor}{\#define isub 0x64}}
\DoxyCodeLine{174 \textcolor{preprocessor}{\#define lsub 0x65}}
\DoxyCodeLine{175 \textcolor{preprocessor}{\#define fsub 0x66}}
\DoxyCodeLine{176 \textcolor{preprocessor}{\#define dsub 0x67}}
\DoxyCodeLine{177 \textcolor{preprocessor}{\#define imul 0x68}}
\DoxyCodeLine{178 \textcolor{preprocessor}{\#define lmul 0x69}}
\DoxyCodeLine{179 \textcolor{preprocessor}{\#define fmul 0x6a}}
\DoxyCodeLine{180 \textcolor{preprocessor}{\#define dmul 0x6b}}
\DoxyCodeLine{181 \textcolor{preprocessor}{\#define idiv 0x6c}}
\DoxyCodeLine{182 \textcolor{preprocessor}{\#define inst\_ldiv 0x6d}}
\DoxyCodeLine{183 \textcolor{preprocessor}{\#define fdiv 0x6e}}
\DoxyCodeLine{184 \textcolor{preprocessor}{\#define ddiv 0x6f}}
\DoxyCodeLine{185 \textcolor{preprocessor}{\#define irem 0x70}}
\DoxyCodeLine{186 \textcolor{preprocessor}{\#define lrem 0x71}}
\DoxyCodeLine{187 \textcolor{preprocessor}{\#define frem 0x72}}
\DoxyCodeLine{188 \textcolor{preprocessor}{\#define inst\_drem 0x73}}
\DoxyCodeLine{189 \textcolor{preprocessor}{\#define ineg 0x74}}
\DoxyCodeLine{190 \textcolor{preprocessor}{\#define lneg 0x75}}
\DoxyCodeLine{191 \textcolor{preprocessor}{\#define fneg 0x76}}
\DoxyCodeLine{192 \textcolor{preprocessor}{\#define dneg 0x77}}
\DoxyCodeLine{193 \textcolor{preprocessor}{\#define ishl 0x78}}
\DoxyCodeLine{194 \textcolor{preprocessor}{\#define lshl 0x79}}
\DoxyCodeLine{195 \textcolor{preprocessor}{\#define ishr 0x7a}}
\DoxyCodeLine{196 \textcolor{preprocessor}{\#define lshr 0x7b}}
\DoxyCodeLine{197 \textcolor{preprocessor}{\#define iushr 0x7c}}
\DoxyCodeLine{198 \textcolor{preprocessor}{\#define lushr 0x7d}}
\DoxyCodeLine{199 \textcolor{preprocessor}{\#define iand 0x7e}}
\DoxyCodeLine{200 \textcolor{preprocessor}{\#define land 0x7f}}
\DoxyCodeLine{201 \textcolor{preprocessor}{\#define ior 0x80}}
\DoxyCodeLine{202 \textcolor{preprocessor}{\#define lor 0x81}}
\DoxyCodeLine{203 \textcolor{preprocessor}{\#define ixor 0x82}}
\DoxyCodeLine{204 \textcolor{preprocessor}{\#define lxor 0x83}}
\DoxyCodeLine{205 \textcolor{preprocessor}{\#define iinc 0x84}}
\DoxyCodeLine{206 \textcolor{preprocessor}{\#define i2l 0x85}}
\DoxyCodeLine{207 \textcolor{preprocessor}{\#define i2f 0x86}}
\DoxyCodeLine{208 \textcolor{preprocessor}{\#define i2d 0x87}}
\DoxyCodeLine{209 \textcolor{preprocessor}{\#define l2i 0x88}}
\DoxyCodeLine{210 \textcolor{preprocessor}{\#define l2f 0x89}}
\DoxyCodeLine{211 \textcolor{preprocessor}{\#define l2d 0x8a}}
\DoxyCodeLine{212 \textcolor{preprocessor}{\#define f2i 0x8b}}
\DoxyCodeLine{213 \textcolor{preprocessor}{\#define f2l 0x8c}}
\DoxyCodeLine{214 \textcolor{preprocessor}{\#define f2d 0x8d}}
\DoxyCodeLine{215 \textcolor{preprocessor}{\#define d2i 0x8e}}
\DoxyCodeLine{216 \textcolor{preprocessor}{\#define d2l 0x8f}}
\DoxyCodeLine{217 \textcolor{preprocessor}{\#define d2f 0x90}}
\DoxyCodeLine{218 \textcolor{preprocessor}{\#define i2b 0x91}}
\DoxyCodeLine{219 \textcolor{preprocessor}{\#define i2c 0x92}}
\DoxyCodeLine{220 \textcolor{preprocessor}{\#define i2s 0x93}}
\DoxyCodeLine{221 \textcolor{preprocessor}{\#define lcmp 0x94}}
\DoxyCodeLine{222 \textcolor{preprocessor}{\#define fcmpl 0x95}}
\DoxyCodeLine{223 \textcolor{preprocessor}{\#define fcmpg 0x96}}
\DoxyCodeLine{224 \textcolor{preprocessor}{\#define dcmpl 0x97}}
\DoxyCodeLine{225 \textcolor{preprocessor}{\#define dcmpg 0x98}}
\DoxyCodeLine{226 \textcolor{preprocessor}{\#define ifeq 0x99}}
\DoxyCodeLine{227 \textcolor{preprocessor}{\#define ifne 0x9a}}
\DoxyCodeLine{228 \textcolor{preprocessor}{\#define iflt 0x9b}}
\DoxyCodeLine{229 \textcolor{preprocessor}{\#define ifge 0x9c}}
\DoxyCodeLine{230 \textcolor{preprocessor}{\#define ifgt 0x9d}}
\DoxyCodeLine{231 \textcolor{preprocessor}{\#define ifle 0x9e}}
\DoxyCodeLine{232 \textcolor{preprocessor}{\#define if\_icmpeq 0x9f}}
\DoxyCodeLine{233 \textcolor{preprocessor}{\#define if\_icmpne 0xa0}}
\DoxyCodeLine{234 \textcolor{preprocessor}{\#define if\_icmplt 0xa1}}
\DoxyCodeLine{235 \textcolor{preprocessor}{\#define if\_icmpge 0xa2}}
\DoxyCodeLine{236 \textcolor{preprocessor}{\#define if\_icmpgt 0xa3}}
\DoxyCodeLine{237 \textcolor{preprocessor}{\#define if\_icmple 0xa4}}
\DoxyCodeLine{238 \textcolor{preprocessor}{\#define if\_acmpeq 0xa5}}
\DoxyCodeLine{239 \textcolor{preprocessor}{\#define if\_acmpne 0xa6}}
\DoxyCodeLine{240 \textcolor{preprocessor}{\#define inst\_goto 0xa7}}
\DoxyCodeLine{241 \textcolor{preprocessor}{\#define jsr 0xa8}}
\DoxyCodeLine{242 \textcolor{preprocessor}{\#define ret 0xa9}}
\DoxyCodeLine{243 \textcolor{preprocessor}{\#define tableswitch 0xaa}}
\DoxyCodeLine{244 \textcolor{preprocessor}{\#define lookupswitch 0xab}}
\DoxyCodeLine{245 \textcolor{preprocessor}{\#define ireturn 0xac}}
\DoxyCodeLine{246 \textcolor{preprocessor}{\#define lreturn 0xad}}
\DoxyCodeLine{247 \textcolor{preprocessor}{\#define freturn 0xae}}
\DoxyCodeLine{248 \textcolor{preprocessor}{\#define dreturn 0xaf}}
\DoxyCodeLine{249 \textcolor{preprocessor}{\#define areturn 0xb0}}
\DoxyCodeLine{250 \textcolor{preprocessor}{\#define inst\_return 0xb1}}
\DoxyCodeLine{251 \textcolor{preprocessor}{\#define getstatic 0xb2}}
\DoxyCodeLine{252 \textcolor{preprocessor}{\#define putstatic 0xb3}}
\DoxyCodeLine{253 \textcolor{preprocessor}{\#define getfield 0xb4}}
\DoxyCodeLine{254 \textcolor{preprocessor}{\#define putfield 0xb5}}
\DoxyCodeLine{255 \textcolor{preprocessor}{\#define invokevirtual 0xb6}}
\DoxyCodeLine{256 \textcolor{preprocessor}{\#define invokespecial 0xb7}}
\DoxyCodeLine{257 \textcolor{preprocessor}{\#define invokestatic 0xb8}}
\DoxyCodeLine{258 \textcolor{preprocessor}{\#define invokeinterface 0xb9}}
\DoxyCodeLine{259 \textcolor{preprocessor}{\#define inst\_new 0xbb}}
\DoxyCodeLine{260 \textcolor{preprocessor}{\#define newarray 0xbc}}
\DoxyCodeLine{261 \textcolor{preprocessor}{\#define anewarray 0xbd}}
\DoxyCodeLine{262 \textcolor{preprocessor}{\#define arraylength 0xbe}}
\DoxyCodeLine{263 \textcolor{preprocessor}{\#define athrow 0xbf}}
\DoxyCodeLine{264 \textcolor{preprocessor}{\#define checkcast 0xc0}}
\DoxyCodeLine{265 \textcolor{preprocessor}{\#define instanceof 0xc1}}
\DoxyCodeLine{266 \textcolor{preprocessor}{\#define monitorenter 0xc2}}
\DoxyCodeLine{267 \textcolor{preprocessor}{\#define monitorexit 0xc3}}
\DoxyCodeLine{268 \textcolor{preprocessor}{\#define wide 0xc4}}
\DoxyCodeLine{269 \textcolor{preprocessor}{\#define multianewarray 0xc5}}
\DoxyCodeLine{270 \textcolor{preprocessor}{\#define ifnull 0xc6}}
\DoxyCodeLine{271 \textcolor{preprocessor}{\#define ifnonnull 0xc7}}
\DoxyCodeLine{272 \textcolor{preprocessor}{\#define goto\_w 0xc8}}
\DoxyCodeLine{273 \textcolor{preprocessor}{\#define jsr\_w 0xc9}}
\DoxyCodeLine{274 }
\DoxyCodeLine{276 \textcolor{preprocessor}{\#define MAIN\_NOME "{}main"{}}}
\DoxyCodeLine{277 \textcolor{preprocessor}{\#define DESCRIPTOR\_MAIN "{}([Ljava/lang/String;)V"{}}}
\DoxyCodeLine{278 \textcolor{preprocessor}{\#define PUBLIC\_STATIC 0x0009}}
\DoxyCodeLine{279 \textcolor{preprocessor}{\#define CLINIT\_NOME "{}<clinit>"{}}}
\DoxyCodeLine{280 \textcolor{preprocessor}{\#define DESCRIPTOR\_CLINIT "{}()V"{}}}
\DoxyCodeLine{281 \textcolor{preprocessor}{\#define STATICCLINIT 0x0008}}
\DoxyCodeLine{282 \textcolor{preprocessor}{\#define INIT\_NOME "{}<init>"{}}}
\DoxyCodeLine{283 \textcolor{preprocessor}{\#define DESCRIPTOR\_INIT "{}()V"{}}}
\DoxyCodeLine{284 }
\DoxyCodeLine{285 \textcolor{preprocessor}{\#define SOURCE\_FILE\_ATTRIBUTE "{}SourceFile"{}}}
\DoxyCodeLine{286 \textcolor{preprocessor}{\#define CODE\_ATTRIBUTE "{}Code"{}}}
\DoxyCodeLine{287 \textcolor{preprocessor}{\#define LINE\_NUMBER\_ATTRIBUTE "{}LineNumberTable"{}}}
\DoxyCodeLine{288 \textcolor{preprocessor}{\#define STACK\_MAP\_ATTRIBUTE "{}StackMapTable"{}}}
\DoxyCodeLine{289 \textcolor{preprocessor}{\#define INNER\_CLASS\_ATTRIBUTE "{}InnerClasses"{}}}
\DoxyCodeLine{290 \textcolor{preprocessor}{\#define SIGNATURE\_ATTRIBUTE "{}Signature"{}}}
\DoxyCodeLine{291 \textcolor{preprocessor}{\#define CONSTANT\_ATTRIBUTE "{}ConstantValue"{}}}
\DoxyCodeLine{292 \textcolor{preprocessor}{\#define EXCEPTIONS\_ATTRIBUTE "{}Exceptions"{}}}
\DoxyCodeLine{293 }
\DoxyCodeLine{294 \textcolor{preprocessor}{\#endif}}

\end{DoxyCode}
